odoo/addons/analytic_tag_dimension_enhanced/README.rst
odoo/addons/analytic_tag_dimension_enhanced/__init__.py
odoo/addons/analytic_tag_dimension_enhanced/__manifest__.py
odoo/addons/analytic_tag_dimension_enhanced/i18n/analytic_tag_dimension_enhanced.pot
odoo/addons/analytic_tag_dimension_enhanced/models/__init__.py
odoo/addons/analytic_tag_dimension_enhanced/models/account_analytic_dimension.py
odoo/addons/analytic_tag_dimension_enhanced/models/account_analytic_tag.py
odoo/addons/analytic_tag_dimension_enhanced/models/analytic_dimension_line.py
odoo/addons/analytic_tag_dimension_enhanced/readme/CONFIGURE.rst
odoo/addons/analytic_tag_dimension_enhanced/readme/CONTRIBUTORS.rst
odoo/addons/analytic_tag_dimension_enhanced/readme/DESCRIPTION.rst
odoo/addons/analytic_tag_dimension_enhanced/static/description/icon.png
odoo/addons/analytic_tag_dimension_enhanced/static/description/index.html
odoo/addons/analytic_tag_dimension_enhanced/tests/__init__.py
odoo/addons/analytic_tag_dimension_enhanced/tests/test_analytic_dimension.py
odoo/addons/analytic_tag_dimension_enhanced/views/account_move_view.xml
odoo/addons/analytic_tag_dimension_enhanced/views/analytic_view.xml
odoo14_addon_analytic_tag_dimension_enhanced-14.0.1.1.2.dist-info/METADATA
odoo14_addon_analytic_tag_dimension_enhanced-14.0.1.1.2.dist-info/WHEEL
odoo14_addon_analytic_tag_dimension_enhanced-14.0.1.1.2.dist-info/top_level.txt
odoo14_addon_analytic_tag_dimension_enhanced-14.0.1.1.2.dist-info/RECORD
