Metadata-Version: 2.1
Name: odoo14-addon-analytic-tag-dimension-enhanced
Version: 14.0.1.1.2
Summary: Analytic Accounts Dimensions Enhanced
Home-page: https://github.com/OCA/account-analytic
Author: Ecosoft, Odoo Community Association (OCA)
Author-email: support@odoo-community.org
License: AGPL-3
Platform: UNKNOWN
Classifier: Programming Language :: Python
Classifier: Framework :: Odoo
Classifier: Framework :: Odoo :: 14.0
Classifier: License :: OSI Approved :: GNU Affero General Public License v3
Requires-Python: >=3.6
Requires-Dist: odoo14-addon-analytic-tag-dimension
Requires-Dist: odoo (<14.1dev,>=14.0a)
